{
  "aiflags": "F_PRIORITIZE_SUPER_EFFECTIVE | F_EVALUATE_ATTACKS | 0",
  "battletype": "SINGLE_BATTLE",
  "items": [
    "ITEM_NONE",
    "ITEM_NONE",
    "ITEM_NONE",
    "ITEM_NONE"
  ],
  "mons": [
    {
      "ability": "COMPOUND_EYES",
      "abilityslot": 0,
      "additionalflags": "0",
      "ballseal": "0",
      "form_index": null,
      "index": 0,
      "ivs": 250,
      "level": 66,
      "moves": [
        "BUG_BUZZ",
        "AGILITY",
        "ABSORB",
        "DISCHARGE"
      ],
      "species": "GALVANTULA",
      "species_token": "SPECIES_GALVANTULA"
    },
    {
      "ability": "SHEER_FORCE",
      "abilityslot": 0,
      "additionalflags": "0",
      "ballseal": "0",
      "form_index": null,
      "index": 1,
      "ivs": 250,
      "level": 66,
      "moves": [
        "FIRE_PUNCH",
        "THRASH",
        "SUPERPOWER",
        "SWAGGER"
      ],
      "species": "DARMANITAN",
      "species_token": "SPECIES_DARMANITAN"
    },
    {
      "ability": "TORRENT",
      "abilityslot": 0,
      "additionalflags": "0",
      "ballseal": "0",
      "form_index": null,
      "index": 2,
      "ivs": 250,
      "level": 66,
      "moves": [
        "HYDRO_PUMP",
        "SURF",
        "EARTHQUAKE",
        "AMNESIA"
      ],
      "species": "SWAMPERT",
      "species_token": "SPECIES_SWAMPERT"
    },
    {
      "ability": "NATURAL_CURE",
      "abilityslot": 0,
      "additionalflags": "0",
      "ballseal": "0",
      "form_index": null,
      "index": 3,
      "ivs": 250,
      "level": 66,
      "moves": [
        "PETAL_DANCE",
        "PETAL_BLIZZARD",
        "GIGA_DRAIN",
        "POISON_STING"
      ],
      "species": "ROSERADE",
      "species_token": "SPECIES_ROSERADE"
    },
    {
      "ability": "INTIMIDATE",
      "abilityslot": 0,
      "additionalflags": "0",
      "ballseal": "0",
      "form_index": null,
      "index": 4,
      "ivs": 250,
      "level": 66,
      "moves": [
        "FLAMETHROWER",
        "PLAY_ROUGH",
        "AGILITY",
        "REVERSAL"
      ],
      "species": "ARCANINE",
      "species_token": "SPECIES_ARCANINE"
    },
    {
      "ability": "DROUGHT",
      "abilityslot": 0,
      "additionalflags": "0",
      "ballseal": "0",
      "form_index": 2,
      "index": 5,
      "ivs": 250,
      "level": 66,
      "moves": [
        "HEAT_WAVE",
        "DRAGON_CLAW",
        "INFERNO",
        "AIR_SLASH"
      ],
      "species": "CHARIZARD",
      "species_token": "SPECIES_CHARIZARD"
    }
  ],
  "nummons": 6,
  "party_id": 773,
  "trainer_id": 773,
  "trainer_name": "Blaze",
  "trainerclass": "TRAINERCLASS_ACE_TRAINER_M",
  "trainermontype": "TRAINER_DATA_TYPE_MOVES | TRAINER_DATA_TYPE_ABILITY | TRAINER_DATA_TYPE_ADDITIONAL_FLAGS"
}