{
  "aiflags": "F_PRIORITIZE_SUPER_EFFECTIVE | F_EVALUATE_ATTACKS | 0",
  "battletype": "SINGLE_BATTLE",
  "items": [
    "ITEM_NONE",
    "ITEM_NONE",
    "ITEM_NONE",
    "ITEM_NONE"
  ],
  "mons": [
    {
      "ability": "LEVITATE",
      "abilityslot": 0,
      "additionalflags": "0",
      "ballseal": "0",
      "form_index": 1,
      "index": 0,
      "ivs": 250,
      "level": 76,
      "moves": [
        "BELCH",
        "HEAT_WAVE",
        "FAIRY_WIND",
        "ASSURANCE"
      ],
      "species": "WEEZING",
      "species_token": "SPECIES_WEEZING"
    },
    {
      "ability": "OVERGROW",
      "abilityslot": 0,
      "additionalflags": "0",
      "ballseal": "0",
      "form_index": null,
      "index": 1,
      "ivs": 250,
      "level": 76,
      "moves": [
        "DRUM_BEATING",
        "BOOMBURST",
        "KNOCK_OFF",
        "UPROAR"
      ],
      "species": "RILLABOOM",
      "species_token": "SPECIES_RILLABOOM"
    },
    {
      "ability": "ADAPTABILITY",
      "abilityslot": 0,
      "additionalflags": "0",
      "ballseal": "0",
      "form_index": 1,
      "index": 2,
      "ivs": 250,
      "level": 76,
      "moves": [
        "METEOR_MASH",
        "DRAGON_PULSE",
        "NASTY_PLOT",
        "CLOSE_COMBAT"
      ],
      "species": "LUCARIO",
      "species_token": "SPECIES_LUCARIO"
    }
  ],
  "nummons": 3,
  "party_id": 901,
  "trainer_id": 901,
  "trainer_name": "Uriel",
  "trainerclass": "TRAINERCLASS_PKMN_RANGER_M",
  "trainermontype": "TRAINER_DATA_TYPE_MOVES | TRAINER_DATA_TYPE_ABILITY | TRAINER_DATA_TYPE_ADDITIONAL_FLAGS"
}