{
  "aiflags": "F_PRIORITIZE_SUPER_EFFECTIVE | F_EVALUATE_ATTACKS | 0",
  "battletype": "SINGLE_BATTLE",
  "items": [
    "ITEM_NONE",
    "ITEM_NONE",
    "ITEM_NONE",
    "ITEM_NONE"
  ],
  "mons": [
    {
      "ability": "BATTLE_ARMOR",
      "abilityslot": 0,
      "additionalflags": "0",
      "ballseal": "0",
      "form_index": null,
      "index": 0,
      "ivs": 250,
      "level": 26,
      "moves": [
        "BUG_BITE",
        "KNOCK_OFF",
        "VENOSHOCK",
        "BITE"
      ],
      "species": "SKORUPI",
      "species_token": "SPECIES_SKORUPI"
    },
    {
      "ability": "SHED_SKIN",
      "abilityslot": 0,
      "additionalflags": "0",
      "ballseal": "0",
      "form_index": null,
      "index": 1,
      "ivs": 250,
      "level": 26,
      "moves": [
        "NIGHT_SLASH",
        "SWAGGER",
        "VENOSHOCK",
        "BITE"
      ],
      "species": "SEVIPER",
      "species_token": "SPECIES_SEVIPER"
    },
    {
      "ability": "OWN_TEMPO",
      "abilityslot": 0,
      "additionalflags": "0",
      "ballseal": "0",
      "form_index": null,
      "index": 2,
      "ivs": 250,
      "level": 26,
      "moves": [
        "SKETCH",
        "SKETCH",
        "SKETCH",
        "SKETCH"
      ],
      "species": "SMEARGLE",
      "species_token": "SPECIES_SMEARGLE"
    },
    {
      "ability": "LEAF_GUARD",
      "abilityslot": 0,
      "additionalflags": "0",
      "ballseal": "0",
      "form_index": null,
      "index": 3,
      "ivs": 250,
      "level": 26,
      "moves": [
        "RAZOR_LEAF",
        "STRING_SHOT",
        "BUG_BITE",
        "TACKLE"
      ],
      "species": "SWADLOON",
      "species_token": "SPECIES_SWADLOON"
    },
    {
      "ability": "HYDRATION",
      "abilityslot": 0,
      "additionalflags": "0",
      "ballseal": "0",
      "form_index": null,
      "index": 4,
      "ivs": 250,
      "level": 26,
      "moves": [
        "MEGA_DRAIN",
        "STRUGGLE_BUG",
        "ACID",
        "PROTECT"
      ],
      "species": "SHELMET",
      "species_token": "SPECIES_SHELMET"
    }
  ],
  "nummons": 5,
  "party_id": 253,
  "trainer_id": 253,
  "trainer_name": "Michael",
  "trainerclass": "TRAINERCLASS_BUG_CATCHER",
  "trainermontype": "TRAINER_DATA_TYPE_MOVES | TRAINER_DATA_TYPE_ABILITY | TRAINER_DATA_TYPE_ADDITIONAL_FLAGS"
}