{
  "aiflags": "F_PRIORITIZE_SUPER_EFFECTIVE | F_EVALUATE_ATTACKS | 0",
  "battletype": "SINGLE_BATTLE",
  "items": [
    "ITEM_NONE",
    "ITEM_NONE",
    "ITEM_NONE",
    "ITEM_NONE"
  ],
  "mons": [
    {
      "ability": "FLUFFY",
      "abilityslot": 0,
      "additionalflags": "0",
      "ballseal": "0",
      "form_index": null,
      "index": 0,
      "ivs": 250,
      "level": 3,
      "moves": [
        "GROWL",
        "TACKLE",
        "TACKLE",
        "TACKLE"
      ],
      "species": "WOOLOO",
      "species_token": "SPECIES_WOOLOO"
    },
    {
      "ability": "STATIC",
      "abilityslot": 0,
      "additionalflags": "0",
      "ballseal": "0",
      "form_index": null,
      "index": 1,
      "ivs": 250,
      "level": 3,
      "moves": [
        "CHARM",
        "THUNDER_SHOCK",
        "TAIL_WHIP",
        "THUNDER_SHOCK"
      ],
      "species": "PICHU",
      "species_token": "SPECIES_PICHU"
    }
  ],
  "nummons": 2,
  "party_id": 8,
  "trainer_id": 8,
  "trainer_name": "Jonathan",
  "trainerclass": "TRAINERCLASS_PKMN_BREEDER_F",
  "trainermontype": "TRAINER_DATA_TYPE_MOVES | TRAINER_DATA_TYPE_ABILITY | TRAINER_DATA_TYPE_ADDITIONAL_FLAGS"
}